Encryption_Decryption_Algorithm/crypto.v
//Top module
module crypto (clk, rst, enable, plain_data, encrypted_data, decrypted_data);
input clk, rst, enable;
input  [7:0] plain_data;
output [7:0] encrypted_data;
output [7:0] decrypted_data;
wire [7:0] key;

LFSR Keygeneration(.clk(clk), .rst(rst), .enable(enable), .keystream(key));
encrypt enc(.d_in(plain_data), .key(key), .d_out(encrypted_data));
decrypt dec(.d_in(encrypted_data), .key(key), .d_out(decrypted_data));
endmodule

// Linear Feedback Shift Register
module LFSR(clk, rst, enable, keystream);
input clk, rst, enable;
output reg [7:0] keystream;
reg [7:0] lfsr;
always @(posedge clk or posedge rst) 
begin
    if(rst)
        lfsr <= 8'b10101100;
    else if(enable)
        lfsr <= {lfsr[6:0], lfsr[7]^lfsr[6]^lfsr[5]^lfsr[4]^lfsr[3]};
end
always @(*)
begin
    keystream = lfsr;
end
endmodule

// S-Box module for encryption
module sbox_encrypt(d_in, d_out);
input  [7:0] d_in;
output [7:0] d_out;
function [3:0] sbox;
    input [3:0] nibble;
    case (nibble)
        4'h0: sbox = 4'h6;  4'h1: sbox = 4'h4;  4'h2: sbox = 4'hC;  4'h3: sbox = 4'h5;
        4'h4: sbox = 4'h0;  4'h5: sbox = 4'h7;  4'h6: sbox = 4'h2;  4'h7: sbox = 4'hE;
        4'h8: sbox = 4'h1;  4'h9: sbox = 4'hF;  4'hA: sbox = 4'h3;  4'hB: sbox = 4'hD;
        4'hC: sbox = 4'h8;  4'hD: sbox = 4'hA;  4'hE: sbox = 4'h9;  4'hF: sbox = 4'hB;
        default: sbox = 4'h0;
    endcase
endfunction
assign d_out = {sbox(d_in[7:4]), sbox(d_in[3:0])};
endmodule

// S-Box for decryption
module sbox_decrypt(d_in, d_out);
input  [7:0] d_in;
output [7:0] d_out;
function [3:0] inv;
    input [3:0] nibble;
    case (nibble)
        4'h6: inv = 4'h0;  4'h4: inv = 4'h1;  4'hC: inv = 4'h2;  4'h5: inv = 4'h3;
        4'h0: inv = 4'h4;  4'h7: inv = 4'h5;  4'h2: inv = 4'h6;  4'hE: inv = 4'h7;
        4'h1: inv = 4'h8;  4'hF: inv = 4'h9;  4'h3: inv = 4'hA;  4'hD: inv = 4'hB;
        4'h8: inv = 4'hC;  4'hA: inv = 4'hD;  4'h9: inv = 4'hE;  4'hB: inv = 4'hF;
        default: inv = 4'h0;
    endcase
endfunction
assign d_out = {inv(d_in[7:4]), inv(d_in[3:0])};
endmodule

//Encryption Module
module encrypt(d_in, key, d_out);
input  [7:0] d_in;
input  [7:0] key;
output [7:0] d_out;
wire [7:0] xor_out, rot_out, sbox_out;

assign xor_out = d_in ^ key;
assign rot_out = {xor_out[6:0], xor_out[7]}; // Left rotate by 1
sbox_encrypt SBOX(.d_in(rot_out), .d_out(sbox_out));
assign d_out = sbox_out;
endmodule

//Decryption Module
module decrypt (d_in, key, d_out);
input  [7:0] d_in;
input  [7:0] key;
output [7:0] d_out;
wire [7:0] invsbox_out, rot_out;

sbox_decrypt INV(.d_in(d_in), .d_out(invsbox_out));
assign rot_out = {invsbox_out[0], invsbox_out[7:1]}; // Right rotate by 1
assign d_out = rot_out ^ key;
endmodule

Encryption_Decryption_Algorithm/crypto_tb.v
module crypto_tb;
    reg clk = 0, rst = 0, enable = 0;
    reg [7:0] plain_data;
    wire [7:0] encrypted_data, decrypted_data;

    crypto uut (.clk(clk), .rst(rst), .enable(enable), .plain_data(plain_data), .encrypted_data(encrypted_data), .decrypted_data(decrypted_data));
    always #5 clk = ~clk;

    initial begin
        $dumpfile("crypto.vcd");
        $dumpvars(0, crypto_tb);
    end
    initial begin
        $display("Time\tPlain\tEncrypted\tDecrypted");
        $monitor("%0dns\t%h\t%h\t\t%h", $time, plain_data, encrypted_data, decrypted_data);
    end
    initial begin
      
        rst = 1; enable = 0; plain_data = 8'h00;
        #5 rst = 0; enable = 1;

        #5 plain_data = 8'hA5; 
        #5 plain_data = 8'h3C; 
        #5 plain_data = 8'hFF; 
        #5 plain_data = 8'h00; 
        #5 plain_data = 8'h69; 
        #10 $finish;
    end

endmodule

Encryption_Decryption_Algorithm/crypto.vcd
$date
	Mon Aug 04 23:25:32 2025
$end
$version
	Icarus Verilog
$end
$timescale
	1s
$end
$scope module crypto_tb $end
$var wire 8 ! decrypted_data [7:0] $end
$var wire 8 " encrypted_data [7:0] $end
$var reg 1 # clk $end
$var reg 1 $ enable $end
$var reg 8 % plain_data [7:0] $end
$var reg 1 & rst $end
$scope module uut $end
$var wire 1 ' clk $end
$var wire 8 ( decrypted_data [7:0] $end
$var wire 1 ) enable $end
$var wire 8 * encrypted_data [7:0] $end
$var wire 8 + key [7:0] $end
$var wire 8 , plain_data [7:0] $end
$var wire 1 - rst $end
$scope module Keygeneration $end
$var wire 1 ' clk $end
$var wire 1 ) enable $end
$var wire 1 - rst $end
$var reg 8 . keystream [7:0] $end
$var reg 8 / lfsr [7:0] $end
$upscope $end
$scope module enc $end
$var wire 8 0 d_in [7:0] $end
$var wire 8 1 d_out [7:0] $end
$var wire 8 2 key [7:0] $end
$var wire 8 3 rot_out [7:0] $end
$var wire 8 4 sbox_out [7:0] $end
$var wire 8 5 xor_out [7:0] $end
$scope module SBOX $end
$var wire 8 6 d_in [7:0] $end
$var wire 8 7 d_out [7:0] $end
$scope function sbox $end
$var reg 4 8 nibble [3:0] $end
$var reg 4 9 sbox [3:0] $end
$upscope $end
$upscope $end
$upscope $end
$scope module dec $end
$var wire 8 : d_in [7:0] $end
$var wire 8 ; d_out [7:0] $end
$var wire 8 < invsbox_out [7:0] $end
$var wire 8 = key [7:0] $end
$var wire 8 > rot_out [7:0] $end
$scope module INV $end
$var wire 8 ? d_in [7:0] $end
$var wire 8 @ d_out [7:0] $end
$scope function inv $end
$var reg 4 A inv [3:0] $end
$var reg 4 B nibble [3:0] $end
$upscope $end
$upscope $end
$upscope $end
$upscope $end
$upscope $end
$enddefinitions $end
#0
$dumpvars
b111 B
b101 A
b1011001 @
b1111111 ?
b10101100 >
b10101100 =
b1011001 <
b0 ;
b1111111 :
b111 9
b101 8
b1111111 7
b1011001 6
b10101100 5
b1111111 4
b1011001 3
b10101100 2
b1111111 1
b0 0
b10101100 /
b10101100 .
1-
b0 ,
b10101100 +
b1111111 *
0)
b0 (
0'
1&
b0 %
0$
0#
b1111111 "
b0 !
$end
#5
b1011001 >
b10110010 <
b10110010 @
b1011 A
b1101 B
b11011100 4
b11011100 7
b11011100 "
b11011100 *
b11011100 1
b11011100 :
b11011100 ?
b1101 9
b1011 8
b10110010 3
b10110010 6
b1011001 5
b0 !
b0 (
b0 ;
b1011001 .
b1011001 +
b1011001 2
b1011001 =
b1011001 /
1$
1)
0&
0-
1#
1'
#10
b10100101 !
b10100101 (
b10100101 ;
b11111100 >
b11111001 <
b11111001 @
b1111 A
b1011 B
b10111111 4
b10111111 7
b10111111 "
b10111111 *
b10111111 1
b10111111 :
b10111111 ?
b1011 9
b1111 8
b11111001 3
b11111001 6
b11111100 5
b10100101 %
b10100101 ,
b10100101 0
0#
0'
#15
b10110011 .
b10110011 +
b10110011 2
b10110011 =
b10110011 /
b111100 !
b111100 (
b111100 ;
b10001111 >
b11111 <
b11111 @
b1 A
b100 B
b1001011 4
b1001011 7
b1001011 "
b1001011 *
b1001011 1
b1001011 :
b1001011 ?
b100 9
b1 8
b11111 3
b11111 6
b10001111 5
b111100 %
b111100 ,
b111100 0
1#
1'
#20
b11111111 !
b11111111 (
b11111111 ;
b1001100 >
b10011000 <
b10011000 @
b1001 A
b1111 B
b11110001 4
b11110001 7
b11110001 "
b11110001 *
b11110001 1
b11110001 :
b11110001 ?
b1111 9
b1001 8
b10011000 3
b10011000 6
b1001100 5
b11111111 %
b11111111 ,
b11111111 0
0#
0'
#25
b1100111 .
b1100111 +
b1100111 2
b1100111 =
b1100111 /
b0 !
b0 (
b0 ;
b1100111 >
b11001110 <
b11001110 @
b1100 A
b1000 B
b10001001 4
b10001001 7
b10001001 "
b10001001 *
b10001001 1
b10001001 :
b10001001 ?
b1000 9
b1100 8
b11001110 3
b11001110 6
b1100111 5
b0 %
b0 ,
b0 0
1#
1'
#30
b1101001 !
b1101001 (
b1101001 ;
b1110 >
b1 A
b100 B
b11100 <
b11100 @
b100 9
b1 8
b1001000 4
b1001000 7
b1001000 "
b1001000 *
b1001000 1
b1001000 :
b1001000 ?
b11100 3
b11100 6
b1110 5
b1101001 %
b1101001 ,
b1101001 0
0#
0'
#35
b10100111 >
b1001111 <
b1001111 @
b100 A
b0 B
b1011 4
b1011 7
b1011 "
b1011 *
b1011 1
b1011 :
b1011 ?
b0 9
b100 8
b1001111 3
b1001111 6
b10100111 5
b1101001 !
b1101001 (
b1101001 ;
b11001110 .
b11001110 +
b11001110 2
b11001110 =
b11001110 /
1#
1'
