ShiftRegister_Project/ShiftRegister.v
module ShiftRegister (
    input clk,
    input rst,
    input ld,
    input shft_en,
    input mode,       // 0: PISO, 1: SIPO
    input dir,        // 0: Right, 1: Left
    input se_in,
    input [3:0] pa_in,
    output reg [3:0] shft_reg,
    output reg [3:0] pa_out,
    output reg se_out
);


always @(posedge clk or posedge rst) begin
    if (rst) begin
        shft_reg <= 4'b0000;
        se_out <= 0;
        pa_out <= 4'b0000;
    end else if (ld) begin
        shft_reg <= pa_in;
    end else if (shft_en) begin
        if (mode == 1'b0) begin  // PISO
            if (dir == 1'b0) begin  // Right shift
                se_out <= shft_reg[0];
                shft_reg <= {1'b0, shft_reg[3:1]};
            end else begin         // Left shift
                se_out <= shft_reg[3];
                shft_reg <= {shft_reg[2:0], 1'b0};
            end
        end else begin  // SIPO
            if (dir == 1'b0) begin  // Right shift-in
                shft_reg <= {se_in, shft_reg[3:1]};
            end else begin         // Left shift-in
                shft_reg <= {shft_reg[2:0], se_in};
            end
        end
    end
    pa_out <= shft_reg;
end

endmodule

ShiftRegister_Project/ShiftRegister_tb.v
module shftregtb;

    reg clk, rst, ld, shft_en, mode, dir;
    reg se_in;
    reg [3:0] pa_in;
    wire [3:0] shft_reg;
    wire [3:0] pa_out;
    wire se_out;

    // Instantiate the shift register module
    ShiftRegister uut (
        .clk(clk),
        .rst(rst),
        .ld(ld),
        .shft_en(shft_en),
        .mode(mode),
        .dir(dir),
        .se_in(se_in),
        .pa_in(pa_in),
        .shft_reg(shft_reg),
        .pa_out(pa_out),
        .se_out(se_out)
    );

    // Clock generation
    always #5 clk = ~clk;

    initial begin
        $dumpfile("ShiftRegister.vcd");
        $dumpvars(0, shftregtb);
    end

    initial begin
        // Monitor internal and external signals
        $monitor("Time=%0t : clk = %b : Mode=%b : Dir=%b : Ld=%b : ShftEn=%b : se_in=%b : pa_in=%b : pa_out=%b : se_out=%b : shftreg=%b",
                 $time, clk, mode, dir, ld, shft_en, se_in, pa_in, pa_out, se_out, shft_reg);

        // Initialize inputs
        clk = 0;
        rst = 1;
        ld = 0;
        shft_en = 0;
        mode = 0;   // 0 = PISO
        dir = 0;    // 0 = shift right, 1 = shift left
        se_in = 0;
        pa_in = 4'b0000;

        // Release reset
        #10 rst = 0;

        // --- PISO Test: Load 1011 and shift right ---
        mode = 0;
        ld = 1; pa_in = 4'b1011; #10;
        ld = 0; shft_en = 1; dir = 0; // Shift right
        #40;

        // Reset before SIPO test
        rst = 1; #10; rst = 0;

        // --- SIPO Test: shift in 1101 left ---
        mode = 1; dir = 1; shft_en = 1;
        se_in = 1; #10;
        se_in = 1; #10;
        se_in = 0; #10;
        se_in = 1; #10;

        $finish;
    end

endmodule

ShiftRegister_Project/ShiftRegister.vcd
$date
	Thu Jul 31 07:32:07 2025
$end
$version
	Icarus Verilog
$end
$timescale
	1s
$end
$scope module shftregtb $end
$var wire 4 ! pa_out [3:0] $end
$var wire 1 " se_out $end
$var wire 4 # shft_reg [3:0] $end
$var reg 1 $ clk $end
$var reg 1 % dir $end
$var reg 1 & ld $end
$var reg 1 ' mode $end
$var reg 4 ( pa_in [3:0] $end
$var reg 1 ) rst $end
$var reg 1 * se_in $end
$var reg 1 + shft_en $end
$scope module uut $end
$var wire 1 , clk $end
$var wire 1 - dir $end
$var wire 1 . ld $end
$var wire 1 / mode $end
$var wire 4 0 pa_in [3:0] $end
$var wire 1 1 rst $end
$var wire 1 2 se_in $end
$var wire 1 3 shft_en $end
$var reg 4 4 pa_out [3:0] $end
$var reg 1 5 se_out $end
$var reg 4 6 shft_reg [3:0] $end
$upscope $end
$upscope $end
$enddefinitions $end
#0
$dumpvars
b0 6
05
bx 4
03
02
11
b0 0
0/
0.
0-
0,
0+
0*
1)
b0 (
0'
0&
0%
0$
b0 #
0"
bx !
$end
#5
b0 4
b0 !
1$
1,
#10
0$
0,
b1011 (
b1011 0
1&
1.
0)
01
#15
b1011 6
b1011 #
1$
1,
#20
0$
0,
1+
13
0&
0.
#25
b1011 4
b1011 !
b101 6
b101 #
15
1"
1$
1,
#30
0$
0,
#35
b101 4
b101 !
b10 6
b10 #
1$
1,
#40
0$
0,
#45
b10 4
b10 !
b1 6
b1 #
05
0"
1$
1,
#50
0$
0,
#55
b1 4
b1 !
b0 6
b0 #
15
1"
1$
1,
#60
b0 4
b0 !
05
0"
0$
0,
1)
11
#65
1$
1,
#70
0$
0,
1*
12
1%
1-
1'
1/
0)
01
#75
b1 6
b1 #
1$
1,
#80
0$
0,
#85
b1 4
b1 !
b11 6
b11 #
1$
1,
#90
0$
0,
0*
02
#95
b11 4
b11 !
b110 6
b110 #
1$
1,
#100
0$
0,
1*
12
#105
b110 4
b110 !
b1101 6
b1101 #
1$
1,
