ALU_Project/ALU.v
module main_ALU(A, B, opcode, Out); // Top main ALU
input [1:0] A;
input [1:0] B;
input [2:0] opcode;
output [1:0] Out;
wire [2:0] ctrl;

CtrlUnit CU(.opcode(opcode), .ctrl(ctrl));
ALU a1(.A(A), .B(B), .ctrl(ctrl), .Out(Out));

endmodule

module CtrlUnit(opcode, ctrl); // Control Unit
input [2:0] opcode;
output reg [2:0] ctrl;

always @(*) 
begin
	case(opcode)
		3'b000: ctrl = 3'b000;
		3'b001: ctrl = 3'b001;
		3'b010: ctrl = 3'b010;
		3'b011: ctrl = 3'b011;
		3'b100: ctrl = 3'b100;
		default: ctrl = 3'bxxx;
	endcase
end
endmodule

module ALU(A, B, ctrl, Out); // ALU
input [1:0] A;
input [1:0] B;
input [2:0] ctrl;
output reg [1:0] Out;

always @(*) 
begin
	case(ctrl)
		3'b000: Out = A+B;
		3'b001: Out = A-B;
		3'b010: Out = A&B;
		3'b011: Out = A|B;
		3'b100: Out = A^B;
		default: Out = 2'bxx;
	endcase
end
endmodule

ALU_Project/ALU_tb.v
module ALU_tb;
reg [1:0] A,B;
reg [2:0] opcode;
wire [1:0] Out;

main_ALU uut(.A(A), .B(B), .opcode(opcode), .Out(Out));

initial begin
$dumpfile("ALU.vcd");
$dumpvars(0,ALU_tb);
end

initial begin
	A = 2'b01; B = 2'b10;

	opcode = 3'b000;
	#10; opcode = 3'b001;
	#10; opcode = 3'b010;
	#10; opcode = 3'b011;
	#10; opcode = 3'b100;
	#10; opcode = 3'b101;

	A = 2'b11; B = 2'b00;

	opcode = 3'b000;
	#10; opcode = 3'b001;
	#10; opcode = 3'b010;
	#10; opcode = 3'b011;
	#10; opcode = 3'b100;
	#10; opcode = 3'b101;
	
	#60; $finish;
end
initial begin
	$monitor("%t, A = %b, B = %b, Opcode = %b, Output = %b",$time, A, B, opcode, Out); 
end
endmodule

ALU_Project/ALU.vcd
$date
	Thu Jul 31 07:40:00 2025
$end
$version
	Icarus Verilog
$end
$timescale
	1s
$end
$scope module ALU_tb $end
$var wire 2 ! Out [1:0] $end
$var reg 2 " A [1:0] $end
$var reg 2 # B [1:0] $end
$var reg 3 $ opcode [2:0] $end
$scope module uut $end
$var wire 2 % A [1:0] $end
$var wire 2 & B [1:0] $end
$var wire 2 ' Out [1:0] $end
$var wire 3 ( ctrl [2:0] $end
$var wire 3 ) opcode [2:0] $end
$scope module CU $end
$var wire 3 * opcode [2:0] $end
$var reg 3 + ctrl [2:0] $end
$upscope $end
$scope module a1 $end
$var wire 2 , A [1:0] $end
$var wire 2 - B [1:0] $end
$var wire 3 . ctrl [2:0] $end
$var reg 2 / Out [1:0] $end
$upscope $end
$upscope $end
$upscope $end
$enddefinitions $end
#0
$dumpvars
b11 /
b0 .
b10 -
b1 ,
b0 +
b0 *
b0 )
b0 (
b11 '
b10 &
b1 %
b0 $
b10 #
b1 "
b11 !
$end
#10
b1 +
b1 (
b1 .
b1 $
b1 )
b1 *
#20
b0 /
b0 !
b0 '
b10 +
b10 (
b10 .
b10 $
b10 )
b10 *
#30
b11 /
b11 !
b11 '
b11 +
b11 (
b11 .
b11 $
b11 )
b11 *
#40
b100 +
b100 (
b100 .
b100 $
b100 )
b100 *
#50
b0 +
b0 (
b0 .
b0 #
b0 &
b0 -
b11 "
b11 %
b11 ,
b0 $
b0 )
b0 *
#60
b1 +
b1 (
b1 .
b1 $
b1 )
b1 *
#70
b0 /
b0 !
b0 '
b10 +
b10 (
b10 .
b10 $
b10 )
b10 *
#80
b11 /
b11 !
b11 '
b11 +
b11 (
b11 .
b11 $
b11 )
b11 *
#90
b100 +
b100 (
b100 .
b100 $
b100 )
b100 *
#100
bx /
bx !
bx '
bx +
bx (
bx .
b101 $
b101 )
b101 *
